{
  "namespaces": [
    "public"
  ],
  "name": "public",
  "tables": [
    {
      "columns": {
        "id": {
          "name": "id",
          "type": "text",
          "unsigned": false,
          "autoincrement": false,
          "primary": true,
          "nullable": false,
          "unique": false,
          "length": null,
          "precision": null,
          "scale": null,
          "default": null,
          "comment": null,
          "enumItems": [],
          "mappedType": "text"
        },
        "order_id": {
          "name": "order_id",
          "type": "text",
          "unsigned": false,
          "autoincrement": false,
          "primary": false,
          "nullable": false,
          "unique": false,
          "length": null,
          "precision": null,
          "scale": null,
          "default": null,
          "comment": null,
          "enumItems": [],
          "mappedType": "text"
        },
        "carrier": {
          "name": "carrier",
          "type": "text",
          "unsigned": false,
          "autoincrement": false,
          "primary": false,
          "nullable": false,
          "unique": false,
          "length": null,
          "precision": null,
          "scale": null,
          "default": null,
          "comment": null,
          "enumItems": [
            "sendcloud",
            "postnl"
          ],
          "mappedType": "enum"
        },
        "service": {
          "name": "service",
          "type": "text",
          "unsigned": false,
          "autoincrement": false,
          "primary": false,
          "nullable": false,
          "unique": false,
          "length": null,
          "precision": null,
          "scale": null,
          "default": null,
          "comment": null,
          "enumItems": [],
          "mappedType": "text"
        },
        "tracking_number": {
          "name": "tracking_number",
          "type": "text",
          "unsigned": false,
          "autoincrement": false,
          "primary": false,
          "nullable": false,
          "unique": false,
          "length": null,
          "precision": null,
          "scale": null,
          "default": null,
          "comment": null,
          "enumItems": [],
          "mappedType": "text"
        },
        "tracking_url": {
          "name": "tracking_url",
          "type": "text",
          "unsigned": false,
          "autoincrement": false,
          "primary": false,
          "nullable": true,
          "unique": false,
          "length": null,
          "precision": null,
          "scale": null,
          "default": null,
          "comment": null,
          "enumItems": [],
          "mappedType": "text"
        },
        "label_url": {
          "name": "label_url",
          "type": "text",
          "unsigned": false,
          "autoincrement": false,
          "primary": false,
          "nullable": true,
          "unique": false,
          "length": null,
          "precision": null,
          "scale": null,
          "default": null,
          "comment": null,
          "enumItems": [],
          "mappedType": "text"
        },
        "label_data": {
          "name": "label_data",
          "type": "jsonb",
          "unsigned": false,
          "autoincrement": false,
          "primary": false,
          "nullable": true,
          "unique": false,
          "length": null,
          "precision": null,
          "scale": null,
          "default": null,
          "comment": null,
          "enumItems": [],
          "mappedType": "json"
        },
        "cost": {
          "name": "cost",
          "type": "numeric",
          "unsigned": false,
          "autoincrement": false,
          "primary": false,
          "nullable": true,
          "unique": false,
          "length": null,
          "precision": null,
          "scale": null,
          "default": null,
          "comment": null,
          "enumItems": [],
          "mappedType": "decimal"
        },
        "currency": {
          "name": "currency",
          "type": "text",
          "unsigned": false,
          "autoincrement": false,
          "primary": false,
          "nullable": false,
          "unique": false,
          "length": null,
          "precision": null,
          "scale": null,
          "default": "'eur'",
          "comment": null,
          "enumItems": [],
          "mappedType": "text"
        },
        "weight": {
          "name": "weight",
          "type": "numeric",
          "unsigned": false,
          "autoincrement": false,
          "primary": false,
          "nullable": false,
          "unique": false,
          "length": null,
          "precision": null,
          "scale": null,
          "default": null,
          "comment": null,
          "enumItems": [],
          "mappedType": "decimal"
        },
        "dimensions": {
          "name": "dimensions",
          "type": "jsonb",
          "unsigned": false,
          "autoincrement": false,
          "primary": false,
          "nullable": true,
          "unique": false,
          "length": null,
          "precision": null,
          "scale": null,
          "default": null,
          "comment": null,
          "enumItems": [],
          "mappedType": "json"
        },
        "from_address": {
          "name": "from_address",
          "type": "jsonb",
          "unsigned": false,
          "autoincrement": false,
          "primary": false,
          "nullable": false,
          "unique": false,
          "length": null,
          "precision": null,
          "scale": null,
          "default": null,
          "comment": null,
          "enumItems": [],
          "mappedType": "json"
        },
        "to_address": {
          "name": "to_address",
          "type": "jsonb",
          "unsigned": false,
          "autoincrement": false,
          "primary": false,
          "nullable": false,
          "unique": false,
          "length": null,
          "precision": null,
          "scale": null,
          "default": null,
          "comment": null,
          "enumItems": [],
          "mappedType": "json"
        },
        "hazmat": {
          "name": "hazmat",
          "type": "boolean",
          "unsigned": false,
          "autoincrement": false,
          "primary": false,
          "nullable": false,
          "unique": false,
          "length": null,
          "precision": null,
          "scale": null,
          "default": "false",
          "comment": null,
          "enumItems": [],
          "mappedType": "boolean"
        },
        "hazmat_type": {
          "name": "hazmat_type",
          "type": "text",
          "unsigned": false,
          "autoincrement": false,
          "primary": false,
          "nullable": true,
          "unique": false,
          "length": null,
          "precision": null,
          "scale": null,
          "default": null,
          "comment": null,
          "enumItems": [
            "lithium",
            "magnetized",
            "dry_ice",
            "other"
          ],
          "mappedType": "enum"
        },
        "status": {
          "name": "status",
          "type": "text",
          "unsigned": false,
          "autoincrement": false,
          "primary": false,
          "nullable": false,
          "unique": false,
          "length": null,
          "precision": null,
          "scale": null,
          "default": "'created'",
          "comment": null,
          "enumItems": [
            "created",
            "picked_up",
            "in_transit",
            "out_for_delivery",
            "delivered",
            "exception",
            "returned"
          ],
          "mappedType": "enum"
        },
        "shipped_at": {
          "name": "shipped_at",
          "type": "timestamptz",
          "unsigned": false,
          "autoincrement": false,
          "primary": false,
          "nullable": true,
          "unique": false,
          "length": 6,
          "precision": null,
          "scale": null,
          "default": null,
          "comment": null,
          "enumItems": [],
          "mappedType": "datetime"
        },
        "delivered_at": {
          "name": "delivered_at",
          "type": "timestamptz",
          "unsigned": false,
          "autoincrement": false,
          "primary": false,
          "nullable": true,
          "unique": false,
          "length": 6,
          "precision": null,
          "scale": null,
          "default": null,
          "comment": null,
          "enumItems": [],
          "mappedType": "datetime"
        },
        "carrier_response": {
          "name": "carrier_response",
          "type": "jsonb",
          "unsigned": false,
          "autoincrement": false,
          "primary": false,
          "nullable": true,
          "unique": false,
          "length": null,
          "precision": null,
          "scale": null,
          "default": null,
          "comment": null,
          "enumItems": [],
          "mappedType": "json"
        },
        "raw_cost": {
          "name": "raw_cost",
          "type": "jsonb",
          "unsigned": false,
          "autoincrement": false,
          "primary": false,
          "nullable": true,
          "unique": false,
          "length": null,
          "precision": null,
          "scale": null,
          "default": null,
          "comment": null,
          "enumItems": [],
          "mappedType": "json"
        },
        "raw_weight": {
          "name": "raw_weight",
          "type": "jsonb",
          "unsigned": false,
          "autoincrement": false,
          "primary": false,
          "nullable": false,
          "unique": false,
          "length": null,
          "precision": null,
          "scale": null,
          "default": null,
          "comment": null,
          "enumItems": [],
          "mappedType": "json"
        },
        "created_at": {
          "name": "created_at",
          "type": "timestamptz",
          "unsigned": false,
          "autoincrement": false,
          "primary": false,
          "nullable": false,
          "unique": false,
          "length": 6,
          "precision": null,
          "scale": null,
          "default": "now()",
          "comment": null,
          "enumItems": [],
          "mappedType": "datetime"
        },
        "updated_at": {
          "name": "updated_at",
          "type": "timestamptz",
          "unsigned": false,
          "autoincrement": false,
          "primary": false,
          "nullable": false,
          "unique": false,
          "length": 6,
          "precision": null,
          "scale": null,
          "default": "now()",
          "comment": null,
          "enumItems": [],
          "mappedType": "datetime"
        },
        "deleted_at": {
          "name": "deleted_at",
          "type": "timestamptz",
          "unsigned": false,
          "autoincrement": false,
          "primary": false,
          "nullable": true,
          "unique": false,
          "length": 6,
          "precision": null,
          "scale": null,
          "default": null,
          "comment": null,
          "enumItems": [],
          "mappedType": "datetime"
        }
      },
      "name": "shipment_record",
      "schema": "public",
      "indexes": [
        {
          "keyName": "IDX_shipment_record_order_id",
          "columnNames": [],
          "composite": false,
          "constraint": false,
          "primary": false,
          "unique": false,
          "expression": "CREATE INDEX IF NOT EXISTS \"IDX_shipment_record_order_id\" ON \"shipment_record\" (\"order_id\") WHERE deleted_at IS NULL"
        },
        {
          "keyName": "IDX_shipment_record_tracking_number",
          "columnNames": [],
          "composite": false,
          "constraint": false,
          "primary": false,
          "unique": false,
          "expression": "CREATE INDEX IF NOT EXISTS \"IDX_shipment_record_tracking_number\" ON \"shipment_record\" (\"tracking_number\") WHERE deleted_at IS NULL"
        },
        {
          "keyName": "IDX_shipment_record_deleted_at",
          "columnNames": [],
          "composite": false,
          "constraint": false,
          "primary": false,
          "unique": false,
          "expression": "CREATE INDEX IF NOT EXISTS \"IDX_shipment_record_deleted_at\" ON \"shipment_record\" (\"deleted_at\") WHERE deleted_at IS NULL"
        },
        {
          "keyName": "shipment_record_pkey",
          "columnNames": [
            "id"
          ],
          "composite": false,
          "constraint": true,
          "primary": true,
          "unique": true
        }
      ],
      "checks": [],
      "foreignKeys": {},
      "nativeEnums": {}
    }
  ],
  "nativeEnums": {}
}
